kalmangps/__init__.py
kalmangps/kalman_processor.py
kalmangps/components/data.py
kalmangps/components/madgwickahrs.py
kalmangps/components/quaternion.py
kalmangps/components/utils.py
kalmangps/components/version.py
kalmangps-0.0.3.dist-info/LICENSE
kalmangps-0.0.3.dist-info/METADATA
kalmangps-0.0.3.dist-info/WHEEL
kalmangps-0.0.3.dist-info/entry_points.txt
kalmangps-0.0.3.dist-info/top_level.txt
kalmangps-0.0.3.dist-info/RECORD
